samgutils/__init__.py
samgutils/add.py
samgutils-0.5.dist-info/LICENSE
samgutils-0.5.dist-info/METADATA
samgutils-0.5.dist-info/WHEEL
samgutils-0.5.dist-info/top_level.txt
samgutils-0.5.dist-info/RECORD
