Metadata-Version: 2.1
Name: samgutils
Version: 0.5
Summary: A Package descr
Author: Luis Liborio
Author-email: lsmliborio@gmail.com
License: MIT
Platform: UNKNOWN
License-File: LICENSE
